kivymd2_widgets/__init__.py
kivymd2_widgets/pickers/__init__.py
kivymd2_widgets/pickers/themepicker/__init__.py
kivymd2_widgets/pickers/themepicker/themepicker.kv
kivymd2_widgets/pickers/themepicker/themepicker.py
kivymd2_widgets-0.0.3.dist-info/LICENSE
kivymd2_widgets-0.0.3.dist-info/METADATA
kivymd2_widgets-0.0.3.dist-info/WHEEL
kivymd2_widgets-0.0.3.dist-info/RECORD
