Metadata-Version: 2.1
Name: kivymd2_widgets
Version: 0.0.3
Summary: Collection of widgets for the older kivymd 1.1.1 lib (material design 2).
License: Apache 2.0
Author: BlackCatDevel0per
Author-email: bcdev@mail.ru
Requires-Python: >=3.8.1,<4.0
Classifier: License :: Other/Proprietary License
Classifier: Programming Language :: Python :: 3
Classifier: Programming Language :: Python :: 3.9
Classifier: Programming Language :: Python :: 3.10
Classifier: Programming Language :: Python :: 3.11
Classifier: Programming Language :: Python :: 3.12
Project-URL: Documentation, https://github.com/BlackCatDevel0per/kivymd2_widgets
Project-URL: Homepage, https://github.com/BlackCatDevel0per/kivymd2_widgets
Project-URL: Repository, https://github.com/BlackCatDevel0per/kivymd2_widgets
